{
	"folders": {},
	"connections": {
		"sqlite_jdbc-18351ea1351-16a29ece97458114": {
			"provider": "sqlite",
			"driver": "sqlite_jdbc",
			"name": "server_base.db3",
			"save-password": true,
			"read-only": false,
			"configuration": {
				"database": "/home/user/Документы/GB curs/Базы данных и PyQT/home_work/progect_messager/server_base.db3",
				"url": "jdbc:sqlite:/home/user/Документы/GB curs/Базы данных и PyQT/home_work/progect_messager/server_base.db3",
				"configurationType": "MANUAL",
				"type": "dev",
				"auth-model": "native",
				"handlers": {}
			}
		}
	},
	"connection-types": {
		"dev": {
			"name": "Разработка",
			"color": "255,255,255",
			"description": "База данных для разработки",
			"auto-commit": true,
			"confirm-execute": false,
			"confirm-data-change": false,
			"auto-close-transactions": false
		}
	}
}